ncrar_eeg_viewer/gui.enaml
ncrar_eeg_viewer/io.py
ncrar_eeg_viewer/main-icon.ico
ncrar_eeg_viewer/main-icon.png
ncrar_eeg_viewer/main.py
ncrar_eeg_viewer/presenter.py
ncrar_eeg_viewer/version.py
ncrar_eeg_viewer-0.0.4.dist-info/licenses/LICENSE.txt
ncrar_eeg_viewer-0.0.4.dist-info/METADATA
ncrar_eeg_viewer-0.0.4.dist-info/WHEEL
ncrar_eeg_viewer-0.0.4.dist-info/entry_points.txt
ncrar_eeg_viewer-0.0.4.dist-info/top_level.txt
ncrar_eeg_viewer-0.0.4.dist-info/RECORD
