Metadata-Version: 2.4
Name: ncrar-eeg-viewer
Version: 0.0.4
Summary: Visualization software for Biosemi data
Author-email: Brad Buran <buran@ohsu.edu>
Maintainer-email: Brad Buran <buran@ohsu.edu>
License: MIT License
Requires-Python: >=3.7
License-File: LICENSE.txt
Requires-Dist: ncrar-audio
Requires-Dist: enaml[qt6-pyside]>=0.13.0
Requires-Dist: biosemi-enaml
Requires-Dist: mne
Requires-Dist: decorators
Dynamic: license-file
